[
    {
        "title": "Wartsila: Comune di Trieste a sostegno dei lavoratori",
        "date_raw": "Fri, 22 Dec 2023 17:03:15 +0100",
        "date": "2023-12-22",
        "url": "https://www.ansa.it/sito/notizie/economia/economia_rss.xml",
        "news_url": "https://www.ansa.it/sito/notizie/economia/2023/12/22/wartsila-comune-di-trieste-a-sostegno-dei-lavoratori_8dced7ce-7954-471d-a83b-e08b2277dab1.html",
        "subtitle": "Approvata mozione urgente a Mimit, Lavoro, Fedriga e D'Agostino",
        "content": "\n                                                \n            Il Consiglio comunale di Trieste\nha approvato una mozione urgente di sostegno ai lavoratori della\nWartsila Italia e di tutti i lavoratori dell'indotto durante una\nseduta del Consiglio comunale. La mozione è stata inviata ai\nMinisteri delle Imprese e del Made in Italy e del Lavoro e delle\nPolitiche Sociali, al Presidente della Regione Fvg Massimiliano\nFedriga e al Presidente dell' Autorità di Sistema Portuale del\nMare Adriatico Orientale Porti Trieste e Monfalcone Zeno\nD'Agostino.\n                                    \n                                       \n\t\t\t\t   La mozione è stata inviata anche alle sigle sindacali\ncoinvolte nella vertenza, affinché \"si trovi una soluzione che\nconsenta di operare con un piano a lungo termine mantenendo la\nfunzione industriale del sito attraverso l'impegno degli Enti\nPubblici coinvolti\". \n                                    \n                                       \n\t\t\t\t          \n                                \n\nRiproduzione riservata © Copyright ANSA\n\n\n\n",
        "ranked": 1,
        "placed": "Economy",
        "epoch": 1703262623.6966186,
        "language": "IT",
        "source": "ANSA"
    },
    {
        "title": "Borsa: Milano poco sopra la parità (-0,04%), bene Tim ed Eni",
        "date_raw": "Fri, 22 Dec 2023 10:22:46 +0100",
        "date": "2023-12-22",
        "url": "https://www.ansa.it/sito/notizie/economia/economia_rss.xml",
        "news_url": "https://www.ansa.it/sito/notizie/economia/2023/12/22/borsa-milano-poco-sopra-la-parita-004-bene-tim-ed-eni_76d721f6-efbe-434c-9232-e993019c571b.html",
        "subtitle": "Pesa lusso",
        "content": "Piazza Affari si muove intorno alla parità nella prima fase della seduta. Il Ftse Mib cede lo 0,04% mentre si mettono in luce Tim (+1,06%) e i titoli del settore petrolifero, questi ultimi grazie soprattutto al rialzo del greggio. Eni guadagna lo 0,84%, Tenaris lo 0,66% e Saipem lo 0,38%.     Appesantiscono il listino invece il lusso di Brunello Cucinelli (-1%) e di Moncler (-0,64%) e, per le prese di beneficio, i bancari Banco Bpm (-0,74%) e Bper (-0,53%).     \n\nRiproduzione riservata © Copyright ANSA\n\n\n\n",
        "ranked": 29,
        "placed": "Economy",
        "epoch": 1703262623.7326245,
        "language": "IT",
        "source": "ANSA"
    },
    {
        "title": "++ La Consob ha oscurato mille siti abusivi in 54 mesi ++",
        "date_raw": "Fri, 22 Dec 2023 09:56:07 +0100",
        "date": "2023-12-22",
        "url": "https://www.ansa.it/sito/notizie/economia/economia_rss.xml",
        "news_url": "https://www.ansa.it/sito/notizie/economia/2023/12/22/-la-consob-ha-oscurato-mille-siti-abusivi-in-54-mesi-_88a1846d-d74d-4a1c-82ce-abe0786f39c5.html",
        "subtitle": "L'ultimo intervento su 5 operatori finanziari non autorizzati",
        "content": "\n                                                \n            La Consob raggiunge il traguardo\ndei mille siti finanziari abusivi oscurati in 54 mesi di\nattività. Lo annuncia la commissione di sorveglianza dei mercati\nche è appena intervenuta su 5 nuovi siti di operatori non\nautorizzati. Si tratta di 'Bitblanco', 'StormInvest',\n'Cryptogo365', 'TCRinvest' ed 'EuroXTradeFX', su cui la\ncommissione ha disposto l'oscuramento a seguito dei poteri che\nle sono stati conferiti dal  'decreto crescita', convertito poi\nnella legge 58 del 28 giugno 2019.\n                                    \n                                       \n\t\t\t\t   Come di consueto in questi casi la Consob richiama\nl'attenzione dei risparmiatori sull'importanza di usare la\n\"massima diligenza\" per effettuare scelte di investimento in\n\"piena consapevolezza\" e ricorda di consutare la sezione 'Occhio\nalle truffe!' presente sul proprio sito internet. \n                                    \n                                       \n\t\t\t\t          \n                                \n\nRiproduzione riservata © Copyright ANSA\n\n\n\n",
        "ranked": 28,
        "placed": "Economy",
        "epoch": 1703262623.754312,
        "language": "IT",
        "source": "ANSA"
    },
    {
        "title": "Euro poco mosso, resta sopra 1,10 dollari+Rpt",
        "date_raw": "Fri, 22 Dec 2023 08:53:20 +0100",
        "date": "2023-12-22",
        "url": "https://www.ansa.it/sito/notizie/economia/economia_rss.xml",
        "news_url": "https://www.ansa.it/sito/notizie/economia/2023/12/22/euro-poco-mosso-resta-sopra-110-dollarirpt_120b2767-8b50-4631-b79f-6f1e1cff9a59.html",
        "subtitle": "(Ripetizione con titolo corretto)",
        "content": "\n                                                \n            Euro poco mosso sul dollaro questa\nmattina sui mercati valutari dopo  aver superato ieri la quota\ndi 1,10 sul dollaro. Oggi la moneta unica europea passa di mano\nsulla divisa americana a 1,1002 con una variazione minima\n(+0,08%). Sullo yen l'euro è a quota 156,49 (+0,02%) \n                                    \n                                       \n\t\t\t\t          \n                                \n\nRiproduzione riservata © Copyright ANSA\n\n\n\n",
        "ranked": 33,
        "placed": "Economy",
        "epoch": 1703262623.769646,
        "language": "IT",
        "source": "ANSA"
    },
    {
        "title": "Lo spread Btp-Bund scende a 160,8 punti in avvio di giornata",
        "date_raw": "Fri, 22 Dec 2023 08:53:15 +0100",
        "date": "2023-12-22",
        "url": "https://www.ansa.it/sito/notizie/economia/economia_rss.xml",
        "news_url": "https://www.ansa.it/sito/notizie/economia/2023/12/22/lo-spread-btp-bund-scende-a-1608-punti-in-avvio-di-giornata_02c92051-5b19-4311-a1c7-e0581e268b83.html",
        "subtitle": "In leggero al 3,58% rialzo il rendimento del decennale italiano",
        "content": "\n                                                \n            Apertura in leggero ribasso per lo\nspread Btp-Bund a 160,8 punti base col rendimento del decennale\nitaliano in marginale rialzo al 3,58% dal 3,57% della chiusura\ndi ieri quando il differenziale col titolo di stato tedesco\naveva concluso a 161,3 punti. \n                                    \n                                       \n\t\t\t\t          \n                                \n\nRiproduzione riservata © Copyright ANSA\n\n\n\n",
        "ranked": 34,
        "placed": "Economy",
        "epoch": 1703262623.7925584,
        "language": "IT",
        "source": "ANSA"
    },
    {
        "title": "Borsa: Milano apre poco variata, Ftse Mib -0,02%",
        "date_raw": "Fri, 22 Dec 2023 09:09:32 +0100",
        "date": "2023-12-22",
        "url": "https://www.ansa.it/sito/notizie/economia/economia_rss.xml",
        "news_url": "https://www.ansa.it/sito/notizie/economia/2023/12/22/borsa-milano-apre-poco-variata-ftse-mib-002_9f816b89-1961-4c7a-b1d9-938ce8356211.html",
        "subtitle": "Indice a 30.268 punti",
        "content": "\n                                                \n            Piazza affari ha aperto la seduta\npoco variata. L'indice Ftse Mib ha segnato un lievissimo calo\npari a -0,02% a 30.268 punti. \n                                    \n                                       \n\t\t\t\t          \n                                \n\nRiproduzione riservata © Copyright ANSA\n\n\n\n",
        "ranked": 32,
        "placed": "Economy",
        "epoch": 1703262623.8056633,
        "language": "IT",
        "source": "ANSA"
    },
    {
        "title": "Borsa: l'Asia cede per nuova stretta di Pechino su giochi online",
        "date_raw": "Fri, 22 Dec 2023 08:44:49 +0100",
        "date": "2023-12-22",
        "url": "https://www.ansa.it/sito/notizie/economia/economia_rss.xml",
        "news_url": "https://www.ansa.it/sito/notizie/economia/2023/12/22/borsa-lasia-cede-per-nuova-stretta-di-pechino-su-giochi-online_2ddb840a-dc32-4680-9775-e11d0c3f7122.html",
        "subtitle": "Tiene Tokyo (+0,09%) dove l'inflazione ha rallentato",
        "content": "\n                                                \n            Seduta nel complesso negativa sui\nlistini asiatici mentre i futures europei e statunitensi sono in\ncalo in attesa dell'inflazione americana che potrebbe\ncontribuire a delineare la prossima politica sui tassi della\nFed.\n                                    \n                                       \n\t\t\t\tA penalizzare le Borse, soprattutto cinesi, sono state le nuove\nlimitazioni annunciate da Pechino suoi giochi online che hanno\ncolpito i maggiori gruppi dell'area  come Tencent e NetEase.\n                                    \n                                       \n\t\t\t\tHong Kong a scambi ancora aperti perde l'1,43%, Shenzhen lo\n0,88% e Shanghai lo 0,14%.\n                                    \n                                       \n\t\t\t\tIn Giappone invece il dato sull'inflazione, che sta rallentando\nsecondo le previsioni (+2,5% l'indice dei prezzi al  consumo\nescluso i cibi freschi) ha sostenuto Tokyo (+0,09%).\n                                    \n                                       \n\t\t\t\tDa segnalare infine che il petrolio sta mettendo a segno il\nmaggiori rialzo  settimanale degli ultimi due mesi per due\nfattori: le navi che evitano di passare dal Mar Rosso a causa\ndell'aumento degli attacchi e l'uscita dell'Angola dall'Opec\ndopo 16 anni che ha sollevato interrogativi sulla tenuta\ndell'organizzazione dei paesi produttori di greggio. \n                                    \n                                       \n\t\t\t\t          \n                                \n\nRiproduzione riservata © Copyright ANSA\n\n\n\n",
        "ranked": 35,
        "placed": "Economy",
        "epoch": 1703262623.8357382,
        "language": "IT",
        "source": "ANSA"
    },
    {
        "title": "Borsa: l'Europa apre in lieve calo, Parigi -0,14%",
        "date_raw": "Fri, 22 Dec 2023 09:21:35 +0100",
        "date": "2023-12-22",
        "url": "https://www.ansa.it/sito/notizie/economia/economia_rss.xml",
        "news_url": "https://www.ansa.it/sito/notizie/economia/2023/12/22/borsa-leuropa-apre-in-lieve-calo-parigi-014_f001783d-597f-4392-a72b-fedc38070860.html",
        "subtitle": "Francoforte poco mossa (-0,08%)",
        "content": "\n                                                \n            Avvio in leggero ribasso sulle\nborse europee. Parigi cede lo 0,14% e Francoforte lo 0,08%.\n                                    \n                                       \n\t\t\t\t\n                                    \n                                       \n\t\t\t\t          \n                                \n\nRiproduzione riservata © Copyright ANSA\n\n\n\n",
        "ranked": 30,
        "placed": "Economy",
        "epoch": 1703262623.8454223,
        "language": "IT",
        "source": "ANSA"
    },
    {
        "title": "Il prezzo del gas sale in avvio ad Amsterdam a 34,4 euro",
        "date_raw": "Fri, 22 Dec 2023 09:21:35 +0100",
        "date": "2023-12-22",
        "url": "https://www.ansa.it/sito/notizie/economia/economia_rss.xml",
        "news_url": "https://www.ansa.it/sito/notizie/economia/2023/12/22/il-prezzo-del-gas-sale-in-avvio-ad-amsterdam-a-344-euro_1f064385-6774-4df5-bc05-1c82f82d31d3.html",
        "subtitle": "il rialzo è pari allo 0,6%",
        "content": "\n                                                \n            Il prezzo del gas sale in avvio di\nseduta ad Amsterdam. Il contratto future Ttf segna un rialzo\ndello 0 ,6% a 34,4 euro al megawattora. \n                                    \n                                       \n\t\t\t\t          \n                                \n\nRiproduzione riservata © Copyright ANSA\n\n\n\n",
        "ranked": 31,
        "placed": "Economy",
        "epoch": 1703262623.8540723,
        "language": "IT",
        "source": "ANSA"
    },
    {
        "title": "Istat, torna a salire la fiducia delle imprese",
        "date_raw": "Fri, 22 Dec 2023 12:06:33 +0100",
        "date": "2023-12-22",
        "url": "https://www.ansa.it/sito/notizie/economia/economia_rss.xml",
        "news_url": "https://www.ansa.it/sito/notizie/economia/2023/12/22/istat-torna-a-salire-la-fiducia-delle-imprese_8b1c0d29-e027-41bc-b992-abb1f169b0c0.html",
        "subtitle": "Dopo 4 mesi consecutivi di ribassi. Aumenta per i consumatori",
        "content": "La frenata dell'inflazione, l'arrivo di tredicesime, di qualche rinnovo contrattuale e il generale clima natalizio alimentano il clima di fiducia dei consumatori e riaccendono quello delle imprese, in calo da quattro mesi.Gli indici stilati dall'Istat segnalano \"un diffuso miglioramento delle opinioni dei consumatori soprattutto sulla situazione economica generale e sulla situazione futura\". Anche le aziende tornano in crescita con un ottimismo che però non contagia la manifattura. Nel dettaglio l' indice delle imprese passa da 103,5 (i minimi dall'aprile 2021) a 107,2. Continua la crescita di quella dei consumatori da 103,6 a 106,7.Numeri che le associazioni dei consumatori Codacons e Unc definiscono \"effetto Natale\" e che rendono più ottimisti anche Confcommercio e Confesercenti per la dinamica dei consumi sia nelle festività sia in prospettiva dei prossimi mesi di inizio 2024. Altri dati positivi o quantomeno che fanno ben sperare, sottolineano, sono quelli del mercato auto, le presenze turistiche (sebbene l'aumento maggiore venga dai turisti stranieri) e, appunto una frenata dei prezzi. Segnali timidi che andrebbero irrobustiti, è il loro ragionamento. con un taglio dei tassi Bce. Una decisione che, tuttavia, non arriverà se non in primavera ma le cui attese hanno indotto allo stop e a un lieve ribasso di tassi sui nuovi mutui.E poi ci sono i lati negativi e le incognite, molte. Il Pil dell'ultimo scorcio dell'anno è in sostanziale stagnazione, sottolineano tutti i principali previsori da Confindustria alla Banca d'Italia e il Fmi. La crescita per il 2023 si dovrebbe fermare allo 0,7% per poi restare sullo stesso livello o risalire fra l'1,1 e l'1,2 a seconda delle stime.Se appunto il turismo (e servizi annessi, come la ristorazione) marciano con il vento in poppa due comparti invece segnano il passo: la manifattura e le costruzioni, quest'ultime senza la spinta del superbonus che il governo e la maggioranza discutono ancora come prolungare per qualche mese e per alcuni soggetti. Un compito che deve associarsi al rigore sui conti pubbliche che, fino a qui, ha mantenuto tranquillità sui mercati finanziari e nelle emissioni di debito pubblico del nostro paese. Il fatturato dell'industria a ottobre, è ancora l'Istat a certificarlo, segna un modesto +0,1% che diviene -1,7% anno su anno e corretto per i giorni di calendarioCerto il saldo della nostra bilancia commerciale con i paesi extra Ue27 è ampiamente positivo e pari a +6.224 milioni (+1.841 milioni a novembre 2022) per l'istituto di statistica. E però sia l'import sia l'export sono in calo. Quello che cambia i numeri è il crollo delle importazioni di energia: -38% a novembre con un notabile -91,8% dalla Russia di Putin. Il deficit energetico dell'Italia cala così a 5,18 miliardi contro gli 8,7 di un anno fa e vedremo se le bollette di famiglie e imprese nel 2024 subiranno un alleggerimento.\n\nRiproduzione riservata © Copyright ANSA\n\n\n\n",
        "ranked": 27,
        "placed": "Economy",
        "epoch": 1703262623.877945,
        "language": "IT",
        "source": "ANSA"
    },
    {
        "title": "Borsa: l'Europa oscilla intorno alla parità, Londra -0,04%",
        "date_raw": "Fri, 22 Dec 2023 10:23:07 +0100",
        "date": "2023-12-22",
        "url": "https://www.ansa.it/sito/notizie/economia/economia_rss.xml",
        "news_url": "https://www.ansa.it/sito/notizie/economia/2023/12/22/borsa-leuropa-oscilla-intorno-alla-parita-londra-004_b5125524-48f3-4a8e-b340-4a8f25e1cd79.html",
        "subtitle": "In luce i petroliferi col rialzo del greggio, arretra il lusso",
        "content": "\n                                                \n            Le Borse europee oscillano intorno\nalla parità in attesa dagli Usa del deflatore Pce core che darà\nuna indicazioni alla Fed sull'andamento dei prezzi al consumo.\n                                    \n                                       \n\t\t\t\tLondra (-0,12%) fai conti col dato finale del Pil nel terzo\ntrimestre nel Regno Unito, contrattosi dello 0,1% rispetto alle\nprevisioni che lo davano invariato, e che aumenta il rischio che\nil Paese finisca in recessione tecnica.\n                                    \n                                       \n\t\t\t\tSena peraltro la stessa perdita Parigi (-0,12%) e peggio fa\nFrancoforte (-0,16%). Nel complesso sono bene intonati i titoli\npetroliferi grazie al rialzo dei prezzi del petrolio e perdono\nterreno quelli del lusso e dei beni di consumo. A Milano\n(-0,06%) la peggiore è Moncler (-0,92%), brillano invece Tenaris\ne Moncler (+0,78% e +0,75%). \n                                    \n                                       \n\t\t\t\t          \n                                \n\nRiproduzione riservata © Copyright ANSA\n\n\n\n",
        "ranked": 25,
        "placed": "Economy",
        "epoch": 1703262623.8864422,
        "language": "IT",
        "source": "ANSA"
    },
    {
        "title": "Istat, torna a salire la fiducia delle imprese ",
        "date_raw": "Fri, 22 Dec 2023 10:24:38 +0100",
        "date": "2023-12-22",
        "url": "https://www.ansa.it/sito/notizie/economia/economia_rss.xml",
        "news_url": "https://www.ansa.it/sito/notizie/economia/2023/12/22/-istat-torna-a-salire-la-fiducia-delle-imprese-_26a2a9b5-098b-4f2d-8997-f53b91d93f8d.html",
        "subtitle": "Dopo 4 mesi consecutivi di ribassi. Aumenta per i consumatori",
        "content": " Dopo quattro mesi consecutivi di ribassi, torna a salire a dicembre la fiducia delle imprese.     L'indice stilato dall'Istat segna un aumento da 103,5 (i minimi dall'aprile 2021) a 107,2. Continua la crescita di quella dei consumatori da 103,6 a 106,7. L'istituto segnala \"un diffuso miglioramento delle opinioni dei consumatori soprattutto sulla situazione economica generale e sulla situazione futura\". Per le imprese \"si segnala un miglioramento della fiducia, seppur con intensità diverse, in tutti i comparti ad eccezione della manifattura\".     \n\nRiproduzione riservata © Copyright ANSA\n\n\n\n",
        "ranked": 26,
        "placed": "Economy",
        "epoch": 1703262623.8972855,
        "language": "IT",
        "source": "ANSA"
    },
    {
        "title": "Al via il corteo per lo sciopero di commercio e turismo",
        "date_raw": "Fri, 22 Dec 2023 10:37:28 +0100",
        "date": "2023-12-22",
        "url": "https://www.ansa.it/sito/notizie/economia/economia_rss.xml",
        "news_url": "https://www.ansa.it/sito/notizie/economia/2023/12/22/al-via-il-corteo-per-lo-sciopero-di-commercio-e-turismo_6b743c9c-87d4-484b-ac55-9c1c9e030482.html",
        "subtitle": "In circa 4000 alla manifestazione",
        "content": "\n                                                \n             E' partito da piazza dell'Esquilino\nil corteo dei lavoratori del commercio e del turismo che oggi\nscioperano per chiedere il rinnovo del contratto, scaduto da\noltre tre anni. A proclamare l'agitazione Filcams Cgil, Fisascat\nCisl e Uiltucs. Il corteo, che vede la partecipazione di circa\n4.000 persone, terminera' a Piazza S.S. Apostoli. \n                                    \n                                       \n\t\t\t\t          \n                                \n\nRiproduzione riservata © Copyright ANSA\n\n\n\n",
        "ranked": 23,
        "placed": "Economy",
        "epoch": 1703262623.9134383,
        "language": "IT",
        "source": "ANSA"
    },
    {
        "title": "De Longhi +3% in Borsa, piace polo delle macchine da caffè",
        "date_raw": "Fri, 22 Dec 2023 10:33:33 +0100",
        "date": "2023-12-22",
        "url": "https://www.ansa.it/sito/notizie/economia/economia_rss.xml",
        "news_url": "https://www.ansa.it/sito/notizie/economia/2023/12/22/de-longhi-3-in-borsa-piace-polo-delle-macchine-da-caffe_bea09439-77e2-456e-b8fc-7864d3cf74e3.html",
        "subtitle": "Il titolo si mette in luce in un listino piatto",
        "content": "\n                                                \n            De Longhi si mette in luce a Piazza\nAffari  dove in un listino piatto il titolo sale del 3% oa 3,6\neuro con una capitlaizzaione di oltre 4,6 miliardi. Il mercato\napprezza l'annuncio, dato ieri a Borsa chiusa, della creazione\ndi un nuovo polo delle macchine da caffè. \n                                    \n                                       \n\t\t\t\t          \n                                \n\nRiproduzione riservata © Copyright ANSA\n\n\n\n",
        "ranked": 24,
        "placed": "Economy",
        "epoch": 1703262623.922131,
        "language": "IT",
        "source": "ANSA"
    },
    {
        "title": "Commercio e turismo in sciopero, protesta in tutte le città",
        "date_raw": "Fri, 22 Dec 2023 11:05:51 +0100",
        "date": "2023-12-22",
        "url": "https://www.ansa.it/sito/notizie/economia/economia_rss.xml",
        "news_url": "https://www.ansa.it/sito/notizie/economia/2023/12/22/commercio-e-turismo-in-sciopero-protesta-in-tutte-le-citta_a34da553-9f1f-47ec-b1a3-e23ee9ef5ee5.html",
        "subtitle": "Terzo Natale con il contratto scaduto per milioni di lavoratori dei servizi in attesa del rinnovo ",
        "content": "E' in corso a Roma il corteo dei lavoratori del commercio e del turismo che oggi scioperano per chiedere il rinnovo del contratto, scaduto da oltre tre anni. A proclamare l'agitazione Filcams Cgil, Fisascat Cisl e Uiltucs. Il corteo, che vede la partecipazione di circa 4.000 persone, terminera' a Piazza S.S. Apostoli.  In corso anche a Napoli la manifestazione interregionale unitaria del Sud dei lavoratori del commercio, del turismo e del terziario delle categorie di Cgil, Cisl e Uil. Il corteo, in partenza da piazza Mancini, nei pressi della Stazione centrale, arriverà a piazza Matteotti dove ci saranno i comizi finali.\"E' una categoria - spiega Giovanni Sgambati, segretario generale Uil Campania e Napoli - da 4 anni senza contratto nazionale. Sono tanti lavoratori, molti dei quali ai limiti della povertà perchè precari o impiegati a tempo parziale e il contratto è l'unico modo per rivalutare i loro salari. Ecco perchè questo sciopero alla vigilia del Natale. In questi mesi le imprese del turismo e del terziario hanno cominciato a macinare forti profitti grazie anche al sacrificio dei lavoratori che devono bene. Questo sarà il terzo Natale con il contratto scaduto per milioni di lavoratori dei servizi in attesa del rinnovo da oltre tre anni. E sarà anche un Natale di lotta con lo sciopero \"Il contratto ci spetta!\" che oggi coinvolgerà terziario, distribuzione moderna organizzata, distribuzione cooperativa, alberghi, pubblici esercizi, ristorazione collettiva e commerciale, agenzie di viaggi e aziende termali. Un totale di oltre 5 milioni di persone sono chiamate alla mobilitazione da Filcams Cgil, Fisascat Cisl e Uiltucs che prevedono un'adesione alta.Comunque \"i negozi saranno aperti\", assicura Federdistribuzione, l'associazione della distribuzione moderna organizzata, impegnata a ridurre al massimo i disagi per i clienti in una delle giornate più calde dell'anno per lo shopping. Federdistribuzione rimarca che lo sciopero \"non aiuta\" in questa fase della trattativa e attende di poter riprendere al più presto \"il confronto su tutti i temi oggetto di negoziazione\".Nei giorni scorsi anche Confcommercio e Confesercenti avevano manifestato la loro disponibilità al confronto immediato \"a tutto tondo\", senza alcuna condizione nella discussione. Le difficoltà del negoziato sarebbero soprattutto sulla parte normativa del contratto, su temi come la stagionalità, la flessibilità negli orari, l'inquadramento professionale, i permessi retribuiti e la quattordicesima.Secondo fonti di Confcommercio, sulla parte salariale, invece, le distanze sarebbero \"non incolmabili\". Anche per alcune fonti sindacali, l'auspicio è quello di poter riprendere la trattativa nelle prime settimane di gennaio per arrivare rapidamente alla firma.Questo sciopero è stato definito \"legittimo e sacrosanto\" dal segretario generale della Cisl, Luigi Sbarra, in un tweet. \"Quando il filo del dialogo si interrompe è giusto mettere in campo tutti gli strumenti di mobilitazione\", scrive Sbarra. Dopo gli scioperi contro la manovra che hanno visto l'adesione solo di Cgil e Uil, i tre sindacati marceranno uniti per i contratti del terziario.Il segretario generale della Uil, Pierluigi Bombardieri, sarà a Roma, alla manifestazione che muoverà da Piazza Esquilino alle 9,30 per arrivare a Piazza Santi Apostoli. Il segretario della Cgil Maurizio Landini e la segretaria generale aggiunta della Cisl, Daniela Fumarola, parteciperanno al corteo di Milano, da piazza Castello a piazza Sempione. I sindacati saranno in piazza anche a Napoli, da piazza Mancini a piazza Matteotti, a Cagliari, in piazza Garibaldi, e Palermo, da piazza Teatro Massimo a via E.Mari.     \n\nRiproduzione riservata © Copyright ANSA\n\n\n\n",
        "ranked": 22,
        "placed": "Economy",
        "epoch": 1703262623.955926,
        "language": "IT",
        "source": "ANSA"
    },
    {
        "title": "Borsa: Europa debole nel finale, bene Wall Street, Milano -0,3%",
        "date_raw": "Thu, 21 Dec 2023 17:25:12 +0100",
        "date": "2023-12-21",
        "url": "https://www.ansa.it/sito/notizie/economia/economia_rss.xml",
        "news_url": "https://www.ansa.it/sito/notizie/economia/2023/12/21/borsa-europa-debole-nel-finale-bene-wall-street-milano-03_97d1ba2a-6137-40ef-bf04-c2794c0e7bfb.html",
        "subtitle": "Ottimismo sui tassi Fed, lo spread risale sopra i 161 punti",
        "content": "\n                                                \n            Europa debole nel finale mentre\nresistono in territorio positivo gli indici dei listini Usa dopo\nl'aumento delle richieste di sussidi e del Pil inferiore alle\nstime. Uno scenario che a diversi operatori appare \"coerente con\nun possibile taglio dei tassi da parte della Fed nel corso del\n2024\". negli ultimi minuti di contrattazioni Milano cede lo\n0,3%, Francoforte lo 0,29%, Parigi lo 0,23%, Londra lo 0,22% e\nMadrid  guadagna lo 0,04%.\n                                    \n                                       \n\t\t\t\t   Risale a 161,3 punti il differenziale tra Btp e Bund\ndecennali tedeschi, con il rendimento annuo italiano in ribasso\ndi 0,2 punti al 3,58% e quello tedesco di 0,2 punti all'1,96%.\n                                    \n                                       \n\t\t\t\tDebole il dollaro a 0,9 euro e 0,79 sterline, in rialzo l'oro\n(+0,45% a 2.043,21 dollari l'oncia), contrastati il greggio (Wti\n-0,85% a 73,6 dollari al barile) e il gas naturale (+2,85% a\n34,5 euro al MWh).\n                                    \n                                       \n\t\t\t\t   Deboli i titoli dell'energia da Shell (-1,4%) a TotalEnergies\n(-0,53%), Bp (-0,45%) ed Eni (-0,38%). Difficoltà per gli\nautomobilistici Volvo (-2,98%), Ferrari (-2,13%), e Volkswagen\n(-1,34%) sull'onda lunga dei dati sulle immatricolazioni di auto\nnei diversi paesi europei. Più cauta Stellantis (-0,07%), di cui\nS&P ha alzato il rating a Bbb+ con prospettiva stabile. \nDifficoltà anche tra i bancari Standard Chartered (-1,12%),\nCredit Agricole (-0,75%), Mps (-0,7%), Banco Bpm (-0,65%)  e\nIntesa (-0,4%). Poco mossa Unicredit (+0,04%), positive\nCommerzbank (+1,14%), dopo il via libera della Bce al riacquisto\ndi titoli, Sabadell (+0,76%) e Bbva (+0,66%). In Piazza Affari\nsprint di Erg (+2,14%), che ha acquistato un portafoglio di\nimpianti eolici e solari negli Usa in partnership con Apex Clean\nEnergy. Rialzi per gli estrattivo-minerari Anglo American\n(+0,77%) e Rio Tinto (+0,64%), più cauto il colosso chimico Basf\n(+0,23%). Contrastato il lusso con Cucinelli (+0,63%), dallo\nscorso 18 dicembre nell'indice Ftse Mib, Moncler (+0,79%), \nBurberry (-4,16%) e Richemont (-1,22%). \n                                    \n                                       \n\t\t\t\t          \n                                \n\nRiproduzione riservata © Copyright ANSA\n\n\n\n",
        "ranked": 54,
        "placed": "Economy",
        "epoch": 1703262624.9312272,
        "language": "IT",
        "source": "ANSA"
    },
    {
        "title": "Borsa: Milano chiude in ribasso, -0,29%",
        "date_raw": "Thu, 21 Dec 2023 17:43:25 +0100",
        "date": "2023-12-21",
        "url": "https://www.ansa.it/sito/notizie/economia/economia_rss.xml",
        "news_url": "https://www.ansa.it/sito/notizie/economia/2023/12/21/borsa-milano-chiude-in-ribasso-029_8e3dd4b8-e4e5-4bec-b525-9ebf556ffa79.html",
        "subtitle": "Indice Ftse Mib a quota 30.274",
        "content": "\n                                                \n            Chiusura in ribasso per Piazza\nAffari. L'indice Ftse Mib ha ceduto lo 0,29% a 30.274 punti.\n                                    \n                                       \n\t\t\t\t\n                                    \n                                       \n\t\t\t\t          \n                                \n\nRiproduzione riservata © Copyright ANSA\n\n\n\n",
        "ranked": 53,
        "placed": "Economy",
        "epoch": 1703262624.9461348,
        "language": "IT",
        "source": "ANSA"
    },
    {
        "title": "Il gas chiude in rialzo a 34,2 euro al MWh al Ttf di Amsterdam",
        "date_raw": "Thu, 21 Dec 2023 18:15:20 +0100",
        "date": "2023-12-21",
        "url": "https://www.ansa.it/sito/notizie/economia/economia_rss.xml",
        "news_url": "https://www.ansa.it/sito/notizie/economia/2023/12/21/il-gas-chiude-in-rialzo-a-342-euro-al-mwh-al-ttf-di-amsterdam_aa4f7ebb-4738-454f-b5d5-ab6d74b849f3.html",
        "subtitle": "I contratti future sul mese di gennaio hanno guadagnato il 2,03%",
        "content": "\n                                                \n            Nuovo rialzo per il gas naturale\nsulla piazza Ttf di Amsterdam. I contratti future sul mese di\ngennaio hanno guadagnato il 2,03% a 34,2 euro al MWh, dopo aver\nsuperato la soglia del 35 euro al traguardo di metà seduta. Sul\nprezzo del metano pesano le tensioni sul Mar Rosso e le tempeste\ndi vento in Gran Bretagna che rallentano le consegne via nave di\ngas naturale liquefatto (Gnl). \n                                    \n                                       \n\t\t\t\t          \n                                \n\nRiproduzione riservata © Copyright ANSA\n\n\n\n",
        "ranked": 49,
        "placed": "Economy",
        "epoch": 1703262624.9541786,
        "language": "IT",
        "source": "ANSA"
    },
    {
        "title": "Cos'è il nuovo Mes, a cui l'Italia ha detto no",
        "date_raw": "Thu, 21 Dec 2023 19:10:29 +0100",
        "date": "2023-12-21",
        "url": "https://www.ansa.it/sito/notizie/economia/economia_rss.xml",
        "news_url": "https://www.ansa.it/sito/notizie/economia/2023/12/21/cose-il-nuovo-mes-a-cui-litalia-ha-detto-no_94ed41b0-446b-4c85-a559-fdbcf9e415ae.html",
        "subtitle": "Più compiti per il meccanismo salva-Stati, anche senza crisi",
        "content": "Il nuovo Meccanismo europeo di stabilità (Mes), che l'Italia non ha ratificato, nasce dal vecchio fondo salva-Stati che l'Ue ha voluto riformare dopo il doloroso salvataggio della Grecia, per rimuoverne le componenti più criticate come l'infausto Memorandum che imponeva tagli e riforme lacrime e sangue in cambio degli aiuti. Archiviata la stagione dell'austerity, l'Ue decise di dare nuovi compiti e poteri al fondo che, per rifarsi un'immagine, avrebbe potuto dare una mano ai Paesi anche prima di finire in crisi.L'idea è stata quindi rafforzare e semplificare l'uso degli strumenti a disposizione del Mes prima del salvataggio di un Paese, ovvero le linee di credito precauzionali: un Paese potrebbe chiederle qualora venisse colpito da uno shock economico e volesse evitare di finire sotto stress sui mercati. La riforma elimina il contestatissimo Memorandum sostituendolo con una lettera d'intenti che assicura il rispetto delle regole del Patto di stabilità. Un problema per i Paesi con deficit e debiti alti: per loro l'unica possibilità sarebbe una linea di credito \"a condizionalità rafforzata\", ovvero che concede aiuti solo a fronte di correzioni dei conti.La riforma affida al Mes anche un altro compito, pensato a tutela dei contribuenti: fornire un paracadute finanziario (backstop) al fondo salva-banche Srf (il fondo unico di risoluzione europeo alimentato dalle banche stesse), qualora, in casi estremi, dovesse finire le risorse a disposizione per completare i 'fallimenti ordinati' delle banche in difficoltà.Si tratta di una linea di credito da 70 miliardi. E' uno dei tasselli mancanti dell'Unione bancaria che tutti i governi italiani, dall'inizio della discussione sulla riforma nel 2018, avevano fortemente voluto.Ma la polemica italiana sul nuovo Mes divampò a fine 2019 a causa della riforma delle 'clausole di azione collettiva' (Cacs) negli eventuali casi di ristrutturazione del debito sovrano di uno Stato membro. In sostanza, con la riforma sarà più semplice ottenere l'ok della platea degli azionisti per approvare la ristrutturazione di un debito sovrano (allungamento delle scadenze, taglio del valore nominale) perché dalle attuali regole che richiedono una doppia maggioranza, si passerà a una maggioranza unica. Per i critici, semplificare le regole per ristrutturare i debiti è una spinta implicita verso una ristrutturazione automatica qualora un Paese in difficoltà dovesse fare richiesta di assistenza al Mes.   \n\nRiproduzione riservata © Copyright ANSA\n\n\n\n",
        "ranked": 46,
        "placed": "Economy",
        "epoch": 1703262624.9623382,
        "language": "IT",
        "source": "ANSA"
    },
    {
        "title": "Eurogruppo, 'rammarico per la decisione di Roma sul Mes'",
        "date_raw": "Thu, 21 Dec 2023 18:03:12 +0100",
        "date": "2023-12-21",
        "url": "https://www.ansa.it/sito/notizie/economia/economia_rss.xml",
        "news_url": "https://www.ansa.it/sito/notizie/economia/2023/12/21/eurogruppo-rammarico-per-la-decisione-di-roma-sul-mes_17576d88-e51a-4551-8ae5-33a1bef01d2e.html",
        "subtitle": "'L'Italia è l'unica a bloccare riforma concordata da tutti'",
        "content": "\n                                                \n            \"Ho preso atto del voto espresso\noggi dal Parlamento italiano in merito alla ratifica del\ntrattato del Mes. Pur nel pieno rispetto delle deliberazioni\nparlamentari,  mi rammarico per l'esito\". Lo afferma il\npresidente dell'Eurogruppo, Paschal Donohoe\n\"L'Italia rimane l'unico Paese che blocca la finalizzazione di\nuna riforma su cui tutti ci siamo impegnati nel 2021\", ricorda\nDonohoe, evidenziando che si tratta di \"un elemento chiave della\nrete di sicurezza comune nell'Eurozona, a vantaggio di tutti i\nPaesi membri\".\n                                    \n                                       \n\t\t\t\t\"Continuerò il mio impegno a riguardo con le autorità italiane\nnei prossimi mesi\", aggiunge il presidente dell'Eurogruppo.\n                                    \n                                       \n\t\t\t\t\n                                    \n                                       \n\t\t\t\t          \n                                \n\nRiproduzione riservata © Copyright ANSA\n\n\n\n",
        "ranked": 52,
        "placed": "Economy",
        "epoch": 1703262624.9833882,
        "language": "IT",
        "source": "ANSA"
    },
    {
        "title": "Lo spread tra Btp e Bund tedeschi chiude in rialzo a 161,3 punti",
        "date_raw": "Thu, 21 Dec 2023 18:07:06 +0100",
        "date": "2023-12-21",
        "url": "https://www.ansa.it/sito/notizie/economia/economia_rss.xml",
        "news_url": "https://www.ansa.it/sito/notizie/economia/2023/12/21/lo-spread-tra-btp-e-bund-tedeschi-chiude-in-rialzo-a-1613-punti_9fd8dc09-1ad8-4860-9e21-e8a70035e137.html",
        "subtitle": "Il rendimento annuo italiano scende di 0,7 punti al 3,57%",
        "content": "\n                                                \n            Ha chiuso in lieve rialzo a 161,3\npunti il differenziale tra Btp e Bund decennali tedeschi, poco\nsopra i 161 punti segnati a fine seduta nella vigilia. Il\nrendimento annuo italiano è sceso di 0,7 punti al 3,57% e quello\ntedesco di 0,6 punti all'1,96%. \n                                    \n                                       \n\t\t\t\t          \n                                \n\nRiproduzione riservata © Copyright ANSA\n\n\n\n",
        "ranked": 50,
        "placed": "Economy",
        "epoch": 1703262624.9952521,
        "language": "IT",
        "source": "ANSA"
    },
    {
        "title": "San Benedetto raggiunge 1 miliardo fatturato, premia dipendenti",
        "date_raw": "Thu, 21 Dec 2023 18:35:49 +0100",
        "date": "2023-12-21",
        "url": "https://www.ansa.it/sito/notizie/economia/economia_rss.xml",
        "news_url": "https://www.ansa.it/sito/notizie/economia/2023/12/21/san-benedetto-raggiunge-1-miliardo-fatturato-premia-dipendenti_1fc30700-430f-414e-9d0a-759201241d51.html",
        "subtitle": "Importo 600 euro sarà riconosciuto a tutti i 2.000 lavoratori",
        "content": "\n                                                \n            San Benedetto spa,ha superato nel\n2023, per la prima volta nella sua storia il miliardo di euro di\nfatturato. Il Cda dela società di acqua minerale di Scorzè\n(Venezia), tramite il presidente Enrico Zoppas, ha espresso\nsoddisfazione per questi risultati, ed ha deciso di erogare  un\npremio a tutti i collaboratori e le collaboratrici del Gruppo,\ncome riconoscimento per il contributo dato al forte sviluppo.\n                                    \n                                       \n\t\t\t\t    Il premio, di 600 euro, sarà riconosciuto a tutti i 2000\ndipendenti degli stabilimenti italiani - Scorzè (Venezia), Paese\n(TV), Pocenia (Udine), Donato (Biella), Popoli (Pescara), Nepi\n(Viterbo), Viggianello (Potenza), Cutolo (Potenza) - nonché a\nquelli degli stabilimenti esteri di Spagna, Polonia e Ungheria;\nsarà erogato nel mese di gennaio 2024 mediante accredito nel\nportale welfare aziendale.\n                                    \n                                       \n\t\t\t\t    La comunicazione ai lavoratori e lavoratricie è avvenuta\ndurante l'incontro annuale per gli auguri di Natale e ha colto\ndi sorpresa - riferisce l'azienda - molti dipendenti presenti\nnella sede di Scorzè e collegati in remoto dagli stabilimenti\nitaliani. \n                                    \n                                       \n\t\t\t\t          \n                                \n\nRiproduzione riservata © Copyright ANSA\n\n\n\n",
        "ranked": 48,
        "placed": "Economy",
        "epoch": 1703262625.0043256,
        "language": "IT",
        "source": "ANSA"
    },
    {
        "title": "Effetto Patto, meno deficit ma la vera sfida è il debito",
        "date_raw": "Thu, 21 Dec 2023 19:58:01 +0100",
        "date": "2023-12-21",
        "url": "https://www.ansa.it/sito/notizie/economia/economia_rss.xml",
        "news_url": "https://www.ansa.it/sito/notizie/economia/2023/12/21/effetto-patto-meno-deficit-ma-la-vera-sfida-e-il-debito_28a8aa5c-3809-470b-802e-6effa6714eca.html",
        "subtitle": "Stretta da 5 miliardi. Tagli e tasse per replicare cuneo e Irpef",
        "content": "La riduzione strutturale del deficit è già nelle tabelle della Nadef, il quadro di previsione della finanza pubblica. Un po' più sfidante, considerato il fardello del Superbonus, il percorso di rientro del debito. Ma certo è che un primo effetto tangibile delle nuove regole del Patto Ue si avrà con la prossima manovra, quando si ridurrà la possibilità di ricorrere all'extradeficit. Una leva che quest'anno ha consentito di prorogare il taglio del cuneo e avviare la nuova Irpef a tre aliquote, ma che ha creato anche un'ipoteca da circa 15 miliardi, che, per essere replicata, andrà coperta con nuove tasse o tagli alla spesa.Per l'Italia l'accordo sottoscritto sul nuovo Patto è \"sostenibile\", ha assicurato il ministro dell'Economia Giancarlo Giorgetti. E infatti il percorso di rientro strutturale del deficit fissato da Bruxelles (cioè una riduzione dello 0,5% annuo) per chi come l'Italia ha un deficit sopra il 3%, è di fatto già messo in conto nelle previsioni per il prossimo triennio: nella Nota di aggiornamento al Def di ottobre, l'indebitamento strutturale si riduce dal -4,8% del 2024 al -4,3% nel 2025, accentuando poi il calo al -3,5% nel 2026.Ma la velocità della correzione può anche prevedere un ammorbidimento: i governi possono infatti concordare con la Commissione una traiettoria tecnica che non blocchi gli investimenti e tenga conto dell'aumento degli interessi. E proprio la possibilità di scontare questa voce, particolarmente pesante per l'Italia, potrebbe tradursi per il nostro Paese in un ritmo di correzione quasi dimezzato, consentendo anche la possibile apertura di nuovi spazi di bilancio rispetto all'attuale quadro. Secondo stime che circolano a Bruxelles, fino al 2027, considerando lo scorporo degli interessi, il peso delle nuove regole sarebbe così di circa 5 miliardi l'anno (ovvero tra lo 0,2 e 0,3%).La vera incognita è rappresentata dal debito. In base alle nuove regole, per i Paesi come il nostro che superano la soglia di un rapporto debito-Pil del 90%, dovrà essere ridotto dell'1% annuo. Un obiettivo al momento difficile da raggiungere. \"La riduzione del debito dell'1% si sarebbe verificata già l'anno prossimo se non ci fosse l'eredità del Superbonus\", spiegava qualche settimana fa Giorgetti. Anche il sentiero di rientro prospettato dalla Nadef disegna un passo di riduzione ancora lontano dall'1%: si passa dal 140,1% del Pil del 2024 al 139,9% nel 2025 e 139,6% nel 2026.Sia sul debito che sul deficit, poi, anche al netto delle nuove regole, pesa l'incognita della crescita: l'andamento dell'economia si sta rivelando inferiore alle attese e quindi le stime sul Pil contenute nella Nadef (+0,8% quest'anno e +1,2% il prossimo) potrebbero essere ridimensionate. Con ricadute anche sulle altre variabili del quadro macroeconomico.  Mettere a punto la manovra 2025 sarà in ogni caso ancora una volta un rebus. I paletti posti dal nuovo Patto, per quanto meno stringenti delle apparenze, consentiranno infatti di utilizzare la leva del deficit meno di quanto fatto finora. Non è un caso che la legge di bilancio per il 2024 sia stata coperta per metà con l'indebitamento proprio in coincidenza con la sospensione delle regole. Per rifinanziare il taglio del cuneo e dell'Irpef si dovrà quindi inevitabilmente guardare anche a coperture concrete, ovvero nuove tasse o interventi di spending review. Una sfida tutt'altro che facile.    \n\nRiproduzione riservata © Copyright ANSA\n\n\n\n",
        "ranked": 45,
        "placed": "Economy",
        "epoch": 1703262625.0223806,
        "language": "IT",
        "source": "ANSA"
    },
    {
        "title": "De Longhi crea il polo del caffè con Eversys e La Marzocco",
        "date_raw": "Thu, 21 Dec 2023 19:37:04 +0100",
        "date": "2023-12-21",
        "url": "https://www.ansa.it/sito/notizie/economia/economia_rss.xml",
        "news_url": "https://www.ansa.it/sito/notizie/economia/2023/12/21/de-longhi-crea-il-polo-del-caffe-con-eversys-e-la-marzocco_a966eba2-8958-4de9-a2f3-038645cc49b6.html",
        "subtitle": "Una newco da 372 milioni di fatturato",
        "content": "\n                                                \n            De' Longhi crea un polo di\nrilevanza mondiale nel segmento delle macchine da caffè\nprofessionali attraverso una business combination tra Eversys e\nLa Marzocco. De' Longhi conferisce in una newco Eversys e il 42%\nde La Marzocco International (acquisito da De Longhi industrial\ne dagli azionisti di minoranza per circa per circa 374 milioni\ndi dollari).  Il gruppo De' Longhi controllerà circa il 61,4%\ndel nuovo polo, mentre quote minoritarie saranno detenute da De\nLonghi Industrial (circa il 26,6%) e dagli attuali azionisti di\nminoranza di LM (complessivamente circa il 12%). Nascerà un polo\nnel caffè professionale con un fatturato aggregato su base\npro-forma previsto nel 2023 di circa 372 milioni ed un adjusted\nEbitda di circa 87 milioni. \n                                    \n                                       \n\t\t\t\t          \n                                \n\nRiproduzione riservata © Copyright ANSA\n\n\n\n",
        "ranked": 44,
        "placed": "Economy",
        "epoch": 1703262625.0307312,
        "language": "IT",
        "source": "ANSA"
    },
    {
        "title": "Borsa: Milano chiude in calo (-0,29%), pesa Ferrari, bene Erg",
        "date_raw": "Thu, 21 Dec 2023 18:50:57 +0100",
        "date": "2023-12-21",
        "url": "https://www.ansa.it/sito/notizie/economia/economia_rss.xml",
        "news_url": "https://www.ansa.it/sito/notizie/economia/2023/12/21/borsa-milano-chiude-in-calo-029-pesa-ferrari-bene-erg_74869b05-83b1-4778-9ae7-1c74a0332ecc.html",
        "subtitle": "Corre calcio quotato",
        "content": "\n                                                \n            Ha chiuso in ribasso Piazza Affari,\ncon l'indice Ftse Mib in calo dello 0,29% a 30.274 punti, tra\nscambi sottili per 1,5 miliardi di euro di controvalore, che\nrisentono ormai dell'imminente pausa natalizia. Pesante Ferrari\n(-2,45%), insieme al resto del comparto auto in Europa\nall'indomani dei dati sulle vendite di auto. Ha fatto meglio\nStellantis (+0,02%), favorita in parte dal rialzo del rating a\n'Bbb+' da parte di S&P. Brillante invece Erg (+2,29%), che ha\nacquistato un portafoglio da 317 Mw di impianti eolici e solari\nnegli Usa in partnership con Apex Clean Energy. Acquisti anche\nsu Tim (+1,66%), al 3/o rialzo consecutivo, che dallo scorso 19\ndicembre è salita di oltre il 7,5%. In progresso i farmaceutici\nDiasorin (+1,27%) e Recordati (+1,13%) e, sul fronte del lusso,\nMoncler (+0,93%) insieme a Cucinelli (+0,86%), ammessa\nnell'indice Ftse Mib dallo scorso 18 dicembre.\n                                    \n                                       \n\t\t\t\t   Deboli A2a (-1,01%), Mediolanum (-0,87%) ed Stm (-0,71%)\ninsieme alla squadra delle banche. Banco Bpm ha ceduto lo 0,7%,\nMps lo 0,59% e Intesa lo 0,27%, mentre ha resistito poco sopra\nla parità Unicredit (+0,04%). Il calo del greggio (Wti -1,5% a\n73,11 dollari al barile) ha penalizzato Tenaris (-0,68%), più\ncaute invece Saipem (-0,28%) ed Eni (-0,03%). Fuori dal paniere\nprincipale hanno corso la Juventus (+5,44%) e la Lazio (+4,49%),\ndopo la sentenza della Corte di Giustizia dell'Ue contro il\nmonopolio di Fifa e Uefa sui\ntornei internazionali tra i club. Due organismi, questi ultimi,\ncontrari al\nprogetto della Superlega, di cui proprio la Juventus è tra le\nsocietà fondatrici. \n                                    \n                                       \n\t\t\t\t          \n                                \n\nRiproduzione riservata © Copyright ANSA\n\n\n\n",
        "ranked": 47,
        "placed": "Economy",
        "epoch": 1703262625.0388536,
        "language": "IT",
        "source": "ANSA"
    },
    {
        "title": "Borsa: Europa debole in chiusura, Parigi -0,16%, Londra -0,27%",
        "date_raw": "Thu, 21 Dec 2023 18:03:19 +0100",
        "date": "2023-12-21",
        "url": "https://www.ansa.it/sito/notizie/economia/economia_rss.xml",
        "news_url": "https://www.ansa.it/sito/notizie/economia/2023/12/21/borsa-europa-debole-in-chiusura-parigi-016-londra-027_45d8db7c-7711-40d8-8a30-100f86133199.html",
        "subtitle": "In calo anche Francoforte (-0,27%), poco variata Madrid (+0,03%)",
        "content": "\n                                                \n            Chiusura debole per le principali\nborse europee. Parigi ha ceduto lo 0,16% a 7.571 punti, Londra\nlo 0,27% a 7.571 punti e Francoforte lo 0,27% a 16.687 punti.\n                                    \n                                       \n\t\t\t\tPoco variata Madrid, che ha guadagnato lo 0,03% a 10.104 punti.\n                                    \n                                       \n\t\t\t\t\n                                    \n                                       \n\t\t\t\t          \n                                \n\nRiproduzione riservata © Copyright ANSA\n\n\n\n",
        "ranked": 51,
        "placed": "Economy",
        "epoch": 1703262625.064994,
        "language": "IT",
        "source": "ANSA"
    },
    {
        "title": "Safilo interrompe l'accordo di licenza con Chiara Ferragni ",
        "date_raw": "Fri, 22 Dec 2023 10:42:36 +0100",
        "date": "2023-12-22",
        "url": "https://www.ansa.it/sito/notizie/economia/economia_rss.xml",
        "news_url": "https://www.ansa.it/sito/notizie/economia/2023/12/21/safilo-interrompe-laccordo-di-licenza-con-chiara-ferragni-_1264e654-a480-482f-95e8-d30da9af97fd.html",
        "subtitle": "'Violati gli impegni contrattuali' per le collezioni eyewear. Gdf acquisisce carte Antitrust su caso Balocco",
        "content": "All'indomani dell'apertura dell'inchiesta della Procura di Milano che ha coinvolto Chiara Ferragni e l'azienda Balocco per la pubblicità del pandoro Pink Christmas, sponsorizzato l'anno scorso dall'influencer con un invito ad acquistarlo a un prezzo di gran lunga superiore a quello di mercato in modo da fare beneficenza, inquirenti e investigatori sono già al lavoro. Il procuratore aggiunto Eugenio Fusco, titolare delle indagini, al momento senza reato né indagati, ha delegato il Nucleo di Polizia Economico Finanziaria della Guardia di Finanza a raccogliere il materiale necessario per avere un quadro della vicenda. Dopo di che, per ulteriori riscontri e chiarimenti, convocherà anche l'imprenditrice cremonese, assistita dai legali dello studio Bana, i quali stamani già di buon ora si sono presentati al quarto piano del Palazzo di Giustizia milanese. Ma intanto sembrano non finire i guai per l'influencer. Safilo Group ha interrotto l'accordo di licenza per il design, la produzione e la distribuzione delle collezioni degli occhiali a marchio Chiara Ferragni \"a seguito\", dice l'azienda, di una presunta \"violazione di impegni contrattuali\". E Fratelli d'Italia chiede che le sia revocato l'Ambrogino d'oro. \"Non eserciterò il veto e lascerò al consiglio comunale ogni tipo di riflessione\" si è limitato a dire il sindaco Giuseppe Sala. Sul caso Balocco, da quanto è traprelato, entro fine anno le Fiamme Gialle si recheranno negli uffici dell'Antitrust per acquisire, senza però alcun ordine di esibizione, i documenti relativi all'istruttoria che si è conclusa nei giorni scorsi con una maxi multa per pratica commerciale scorretta: oltre un milione la sanzione per due società riconducibili alla nota blogger, Fenice e TBS Crew - The blonde salad, e 420mila euro per i produttori del dolce natalizio. Inoltre saranno anche acquisiti, o più probabilmente consegnati dagli avvocati della moglie di Fedez, i contratti stipulati con l'azienda di Cuneo, tutte le mail scambiate o altri documenti relativi all'operazione che, stando alla pubblicità, avrebbe dovuto portare a devolvere una somma rilevante per le cure dei piccoli pazienti in cura nella struttura torinese. Tutto questo per cercare di far luce sul caso e capire se ci sia stato davvero, come la influencer ha affermato nel suo video di scuse, prima di sparire dai social, un \"errore di comunicazione\" in cui sono state mischiate, è questo il senso, \"attività di beneficenza, che ho sempre fatto e continuerò a fare, da attività commerciali\". Con questo quadro, a meno di qualche sorpresa nel corso delle indagini, sarebbe \"impraticabile\" contestare la truffa mentre invece potrebbe essere ipotizzata una frode in commercio legata alla \"qualità etica\" del \"bene mobile\", ossia del pandoro venduto. Infine gli accertamenti potrebbero estendersi anche alla vicenda simile della pubblicità delle uova di Pasqua della Dolci Preziosi Il fascicolo è stato aperto dopo un esposto del Codacons e di Assourt in cui si sostiene che siano stati truffati \"una pluralità di individui\", ossia i consumatori. Esposto depositato in 104 Procure e quella di Milano, a quanto risulta, è stata la prima a muoversi, seguita da Cuneo dove ha sede la Balocco.\n\nRiproduzione riservata © Copyright ANSA\n\n\n\n",
        "ranked": 41,
        "placed": "Economy",
        "epoch": 1703262625.0821817,
        "language": "IT",
        "source": "ANSA"
    },
    {
        "title": "Borsa: Piazza Affari si conferma sui massimi dal giugno del 2008",
        "date_raw": "Thu, 21 Dec 2023 20:08:57 +0100",
        "date": "2023-12-21",
        "url": "https://www.ansa.it/sito/notizie/economia/economia_rss.xml",
        "news_url": "https://www.ansa.it/sito/notizie/economia/2023/12/21/borsa-piazza-affari-si-conferma-sui-massimi-dal-giugno-del-2008_5f8c7d38-cd28-4560-8e59-ba3f737e50f6.html",
        "subtitle": "Nonostante il calo odierno l'indice Ftse Mib sopra 30mila punti",
        "content": "\n                                                \n            Piazza Affari si conferma sui\nmassimi dal giugno del 2008, dopo una serie di alti e bassi a\ncavallo dei 30 mila punti iniziata lo scorso 1 dicembre.\n                                    \n                                       \n\t\t\t\tL'indice Ftse Mib ha chiuso oggi con un calo dello 0,29% a\n30.274 punti, poco sotto i  30.363 punti dello scorso 19\ndicembre, toccati l'ultima volta il 19 giugno del 2008. Da\ninizio anno l'indice principale di Piazza Affari guadagna il\n27,7%, confermandosi il migliore tra quelli delle principali\npiazze finanziarie europee. \n                                    \n                                       \n\t\t\t\t          \n                                \n\nRiproduzione riservata © Copyright ANSA\n\n\n\n",
        "ranked": 42,
        "placed": "Economy",
        "epoch": 1703262625.0907533,
        "language": "IT",
        "source": "ANSA"
    },
    {
        "title": "A giugno le procedure per deficit eccessivo, Patto dal 2025",
        "date_raw": "Thu, 21 Dec 2023 20:02:33 +0100",
        "date": "2023-12-21",
        "url": "https://www.ansa.it/sito/notizie/economia/economia_rss.xml",
        "news_url": "https://www.ansa.it/sito/notizie/economia/2023/12/21/a-giugno-le-procedure-per-deficit-eccessivo-patto-dal-2025_760e0d7e-57be-48be-92dc-05ad14049006.html",
        "subtitle": "Consiglio Ue adotta le nuove norme, parte l'iter legislativo",
        "content": " Per ora l'appuntamento più importante è fissato per metà giugno 2024 dopo lo svolgimento delle elezioni europee. La Commissione Ue presenterà le sue raccomandazioni sullo stato di salute dei conti pubblici nazionali nonché la lista dei Paesi destinati a essere oggetto di una procedura per deficit eccessivo perché il loro disavanzo nel 2023 ha superato il 3% del Pil. Un esercizio che riguarderà almeno una decina di Paesi, fanno sapere a Bruxelles, tra cui l'Italia e la Francia. Ma il percorso a tappe che ha preso il via con l'intesa politica sulla riforma del Patto di stabilità e l'adozione dei relativi testi legislativi da parte del Consiglio Ue (due regolamenti e una direttiva), sarà inizialmente marcato da un ritorno al passato. In attesa che entrino in vigore le nuove regole, dal primo gennaio prossimo - salvo colpi di scena - tornerà in vigore il vecchio Patto.Il nuovo quadro normativo, se non ci saranno intoppi, dovrebbe essere invece approvato entro aprile - cioè prima della fine della legislatura - dopo che tra gennaio e marzo si saranno svolti i negoziati con l'Europarlamento. Con l'obiettivo di essere poi applicato a partire dal 2025. Anche se non è ancora chiaro se inciderà già sulle leggi di bilancio nazionali che saranno predisposte per quell'anno.\"Nei prossimi mesi dovranno essere definite le modalità con cui applicare le disposizioni del nuovo Patto nel 2025\", ha spiegato un addetto ai lavori. Di sicuro, ha aggiunto la stessa fonte, i Paesi che finiranno in procedura per deficit eccessivo temporaneamente avranno come unico vincolo quello di ridurre dello 0,5% il deficit strutturale ma tenendo conto del peso degli interessi sul debito.Una flessibilità introdotta in diversi passaggi del nuovo quadro normativo che a Bruxelles tengono a rivendicare. \"E' vero che l'obiettivo della semplificazione non è stato raggiunto a causa delle richieste avanzate dalla Germania e da altri Paesi.Ma è anche vero che sono stati introdotti elementi di flessibilità ed è stato dato spazio agli investimenti\". Le traiettorie di rientro dei conti pubblici che saranno definite dalla Commissione terranno infatti conto di fattori rilevanti come le spese per la difesa, il Pnrr, la necessità di non strangolare gli investimenti strategici e il costo degli interessi sul debito. Ed è stata anche abolita la clausola - ritenuta inaccettabile e irrealistica non solo dall'Italia - che prevedeva il taglio del debito di un ventesimo all'anno.    \n\nRiproduzione riservata © Copyright ANSA\n\n\n\n",
        "ranked": 43,
        "placed": "Economy",
        "epoch": 1703262625.113339,
        "language": "IT",
        "source": "ANSA"
    },
    {
        "title": "Borsa: Tokyo, apertura in rialzo (+0,31%)",
        "date_raw": "Fri, 22 Dec 2023 01:35:10 +0100",
        "date": "2023-12-22",
        "url": "https://www.ansa.it/sito/notizie/economia/economia_rss.xml",
        "news_url": "https://www.ansa.it/sito/notizie/economia/2023/12/22/borsa-tokyo-apertura-in-rialzo-031_26c48949-5547-4de5-a038-f7867d067fa1.html",
        "subtitle": "Nikkei segue ripresa Wall Street, attesa dati inflazione Usa",
        "content": "\n                                                \n            La Borsa di Tokyo apre l'ultima\nseduta della settimana col segno più in scia all'ottimismo sul\nmercato azionario statunitense, e in attesa delle indicazioni\ndall'inflazione. Il listino di riferimento Nikkei avanza dello\n0,31% a quota 33.242,39, aggiungendo 101 punti. Sul fronte\nvalutario lo yen torna a stabilizzarsi sul dollaro a un livello\ndi poco superiore a 142, e sull'euro a 156,30. \n                                    \n                                       \n\t\t\t\t          \n                                \n\nRiproduzione riservata © Copyright ANSA\n\n\n\n",
        "ranked": 40,
        "placed": "Economy",
        "epoch": 1703262625.1400266,
        "language": "IT",
        "source": "ANSA"
    },
    {
        "title": "Euro poco mosso, sopra scambiato a 1,10 dollari",
        "date_raw": "Fri, 22 Dec 2023 08:40:38 +0100",
        "date": "2023-12-22",
        "url": "https://www.ansa.it/sito/notizie/economia/economia_rss.xml",
        "news_url": "https://www.ansa.it/sito/notizie/economia/2023/12/22/euro-poco-mosso-sopra-scambiato-a-110-dollari_c55a1a50-b133-4f61-8365-496e58ca19ed.html",
        "subtitle": "Sullo yen, passa di mano a 156,49",
        "content": "\n                                                \n            Euro poco mosso sul dollaro questa\nmattina sui mercati valutari dopo  aver superato ieri la quota\ndi 1,10 sul dollaro. Oggi la moneta unica europea passa di mano\nsulla divisa americana a 1,1002 con una variazione minima\n(+0,08%). Sullo yen l'euro è a quota 156,49 (+0,02%) \n                                    \n                                       \n\t\t\t\t          \n                                \n\nRiproduzione riservata © Copyright ANSA\n\n\n\n",
        "ranked": 36,
        "placed": "Economy",
        "epoch": 1703262625.1559803,
        "language": "IT",
        "source": "ANSA"
    },
    {
        "title": "Cna, dalle vacanze di Natale-Capodanno giro d'affari 18 miliardi",
        "date_raw": "Fri, 22 Dec 2023 17:08:06 +0100",
        "date": "2023-12-22",
        "url": "https://www.ansa.it/sito/notizie/economia/economia_rss.xml",
        "news_url": "https://www.ansa.it/sito/notizie/economia/2023/12/22/cna-da-vacanze-natale-capodanno-giro-daffari-18-miliardi_66f07998-c035-4cee-8b83-7f5d48ec4e15.html",
        "subtitle": "15 milioni di pernottamenti, a trainare cultura, \"radici\", sci",
        "content": "In montagna ma soprattutto nei borghi, nelle città e piccoli centri d'arte, nei paesi di origine, alla ricerca delle proprie radici: la ministra del Turismo lo sintetizza, \"tornano le vacanze di Natale\". E riportano tante risorse e giro d'affari per tutte le imprese legate, anche in via indiretta, al turismo e all'enogastronomia. Il dato è impressionante: diciotto miliardi di euro. A tanto ammonta infatti il movimento del turismo in Italia nelle festività di Natale e Capodanno, tra il 22 dicembre e il 2 gennaio.Un'indagine di Cna Turismo e Commercio spiega che questa montagna di soldi sarà alimentata dai 7 milioni di turisti attesi per le feste: 4,5 milioni gli italiani e 2,5 milioni gli stranieri, ai quali si aggiungeranno gli \"escursionisti\", quanti cioè non pernottano fuori casa ma si limitano a una giornata fuori. In totale saranno 15 milioni i pernottamenti, dei quali nove milioni a carico dei turisti italiani e il resto degli stranieri. \"Queste rilevazioni evidenziano che nei periodi di alta stagione i dati continuano a essere ottimi\" esulta la ministra del Turismo. Incrociando i dati che arrivano dalle associazioni di settore, si scopre che almeno un italiano su 5 (il 20%) ha deciso di trascorrere almeno un giorno fuori casa durante le festività di Natale. Per Coldiretti/Ixe' gli italiano mostrano un deciso orientamento a rimanere in Italia, scelta quest'anno come meta dal 75% dei vacanzieri. Ma anche di provare a risparmiare sui pernottamenti: l'alloggio più gettonato è la casa di parenti e amici, dove passerà le vacanze oltre un italiano su 3 (35%), più un 6% che userà le seconde case di proprietà. Alberghi e appartamenti in affitto sono, a pari merito, al secondo posto. Con le vacanze tornano anche le probabili code sulle strade: l'Anas avverte che saranno 6,5 milioni le persone che si metteranno in viaggio su strade e autostrade, da cui per facilitare lo scorrimento verranno rimossi 171 cantieri.La prevista crescita del traffico sarà del 20%. La tradizione, ovviamente, premia la gastronomia e a giudicare dalle previsioni queste feste finiranno in un'abbuffata. E per fortuna che c'è stato l'intervento dei Nas che ha portato al sequestro di 39 tonnellate di prodotti dolciari e materie prime avariati o mal conservati. Anche se non c'è occasione conviviale che valga quanto il pranzo di Natale, nettamente preferito dalla metà degli italiani rispetto al cenone della Vigilia, prescelto, assicura la Cna Agroalimentare, solamente da un terzo della popolazione, la spesa degli italiani per il pesce arriverà a 1,1 miliardi di euro, (dati di Cia-Agricoltori Italiani e PescAgri), malgrado listini in aumento annuale del 10% sui mercati ittici. Ma questo Natale conferma però per il secondo anno consecutivo che l'alimento più amato nel periodo delle feste, dopo i dolci, saranno i formaggi: gli italiani, dati Afidop, ci spenderanno 400 milioni di euro per portare in tavola 30mila tonnellate di prodotto. Più o meno la spesa prevista da Confcooperative per l'acquisto di dolci. In generale, l'organizzazione cooperativa ha stimato che per il cenone di Natale gli italiani spenderanno 2,9 miliardi, 400 milioni in più dello scorso anno. Senza farsi mancare però qualche \"ristoro\" in agriturismo, a tavola e in fattoria: saranno oltre 2 milioni di nuclei, fatti di parenti e amici, a sceglierli tra Natale e Capodanno, secondo i calcoli di Cia-Agricoltori insieme a Turismo Verde.\n\nRiproduzione riservata © Copyright ANSA\n\n\n\n",
        "ranked": 21,
        "placed": "Economy",
        "epoch": 1703262625.1739821,
        "language": "IT",
        "source": "ANSA"
    },
    {
        "title": "A Unicredit la rigenerazione dello scalo Farini a Milano",
        "date_raw": "Fri, 22 Dec 2023 11:27:07 +0100",
        "date": "2023-12-22",
        "url": "https://www.ansa.it/sito/notizie/economia/economia_rss.xml",
        "news_url": "https://www.ansa.it/sito/notizie/economia/2023/12/22/a-unicredit-la-rigenerazione-dello-scalo-farini-a-milano_c25fd183-47ae-4784-864c-71e40bdfd152.html",
        "subtitle": "Con Prelios e Hines. Orcel, 'impegno per futuro dell'Italia''",
        "content": "\n                                                \n            UniCredit, supportata da Prelios e\nHines si è aggiudicata la gara indetta da FS Sistemi Urbani per\nla cessione di due aree ferroviarie dismesse nella città di\nMilano - Scalo Farini e Scalo San Cristoforo, per una superficie\ntotale di circa 620mila metri quadri - in cui UniCredit guiderà\nuna delle più rilevanti iniziative di rigenerazione urbana in\nEuropa, sostenendo il futuro sviluppo della città.\n                                    \n                                       \n\t\t\t\t   Il progetto Scalo Farini ha l'ambizione di ridefinire il modo\nsostenibile di lavorare e vivere a Milano, creando un nuovo\nquartiere sostenibile con ampi spazi verdi che integrerà uffici,\nabitazioni, negozi e servizi (Accademia di Brera, scuole,\nhotel). Lo sviluppo dello Scalo Farini includerà anche il nuovo\nCampus UniCredit.\n                                    \n                                       \n\t\t\t\t    \"Questa iniziativa metterà UniCredit in prima linea nella\npiù importante opera di rigenerazione urbana degli ultimi anni,\nlasciando un segno nello sviluppo della comunità. È una\ntestimonianza di impegno per il futuro dell'Italia e per le\npotenzialità di Milano ed è un esempio tangibile di come viviamo\nil nostro obiettivo di far progredire le comunità\", ha\ndichiarato Andrea Orcel, amministratore delegato del gruppo\nbancario. \n                                    \n                                       \n\t\t\t\t          \n                                \n\nRiproduzione riservata © Copyright ANSA\n\n\n\n",
        "ranked": 20,
        "placed": "Economy",
        "epoch": 1703262625.1829538,
        "language": "IT",
        "source": "ANSA"
    },
    {
        "title": "Giappone: inflazione rallenta al 2,5% in novembre",
        "date_raw": "Fri, 22 Dec 2023 03:12:48 +0100",
        "date": "2023-12-22",
        "url": "https://www.ansa.it/sito/notizie/economia/economia_rss.xml",
        "news_url": "https://www.ansa.it/sito/notizie/economia/2023/12/22/giappone-inflazione-rallenta-al-25-in-novembre_02213efc-0dbf-4aa7-ab12-209f36fbdb09.html",
        "subtitle": "Sopra obiettivo del 2% della BoJ per ventesimo mese consecutivo",
        "content": "\n                                                \n            I sussidi del governo sulle bollette\nenergetiche contribuiscono al rallentamento dell'inflazione in\nGiappone, il più pronunciato da luglio 2022. Nel mese di\nnovembre l'indice dei prezzi al consumo si assesta al 2,5%, dal\n2,9% di ottobre, comunque sopra l'obiettivo del 2% della Banca\ncentrale (BoJ) per il ventesimo mese consecutivo, con i costi\ndegli affitti a guidare i rialzi più consistenti, pari al 62,9%,\nmentre i prezzi dell'energia sono diminuiti del 10,1%. I dati\ngiungono a pochi giorni dalla decisione della BoJ di mantenere\nla politica monetaria ultra-espansiva, e la progressiva perdita\ndi valore dello yen sulle principali valute, rendendo più\ncostose le importazioni. Il governatore dell'istituto, Kazuo\nUeda, ha affermato che è necessario \"un circolo virtuoso di\nsalari e prezzi\" per raggiungere l'obiettivo di inflazione della\nbanca centrale, facendo riferimento al previsto miglioramento\ndegli stipendi di numerose categorie di lavoratori all'inizio\ndel prossimo anno, a seguito delle tradizionali trattative\nannuali dei sindacati. \n                                    \n                                       \n\t\t\t\t          \n                                \n\nRiproduzione riservata © Copyright ANSA\n\n\n\n",
        "ranked": 39,
        "placed": "Economy",
        "epoch": 1703262625.193,
        "language": "IT",
        "source": "ANSA"
    },
    {
        "title": "Prezzo oro poco mosso a 2.047 dollari l'oncia",
        "date_raw": "Fri, 22 Dec 2023 08:11:32 +0100",
        "date": "2023-12-22",
        "url": "https://www.ansa.it/sito/notizie/economia/economia_rss.xml",
        "news_url": "https://www.ansa.it/sito/notizie/economia/2023/12/22/prezzo-oro-poco-mosso-a-2.047-dollari-loncia_9b4411fa-3948-4283-a8f6-bfc73059d4d5.html",
        "subtitle": "Quotazione cresce dello 0,09%",
        "content": "\n                                                \n            Prezzo dell'oro poco mosso questa\nmattina sui mercati delle materie prime: il metallo prezioso con\nconsegna immediata è scambiato a 2.047 dollari l'oncia con una\ncrescita dello 0,09%. \n                                    \n                                       \n\t\t\t\t          \n                                \n\nRiproduzione riservata © Copyright ANSA\n\n\n\n",
        "ranked": 37,
        "placed": "Economy",
        "epoch": 1703262625.2208202,
        "language": "IT",
        "source": "ANSA"
    },
    {
        "title": "Prezzo del petrolio in aumento, Brent torna sopra 80 dollari",
        "date_raw": "Fri, 22 Dec 2023 08:10:49 +0100",
        "date": "2023-12-22",
        "url": "https://www.ansa.it/sito/notizie/economia/economia_rss.xml",
        "news_url": "https://www.ansa.it/sito/notizie/economia/2023/12/22/prezzo-del-petrolio-in-aumento-brent-torna-sopra-80-dollari_2b9b3508-0d06-4159-bff1-74bf4c291ec2.html",
        "subtitle": "Wti a 74,53 dollari al barile",
        "content": "\n                                                \n            Le tensioni geopolitiche e la\nsituazione nel Mar Rosso  spinge il prezzo del petrolio stamani\nin lieve crescita. Il greggio Wti del Texas passa di mano a\n74,53 dollari al barile, in aumento dello 0,87%, mentre il Brent\ndel Mare del Nord torna sopra la soglia degli 80 dollari, a\n80,03 dollari al barile. \n                                    \n                                       \n\t\t\t\t          \n                                \n\nRiproduzione riservata © Copyright ANSA\n\n\n\n",
        "ranked": 38,
        "placed": "Economy",
        "epoch": 1703262625.2332287,
        "language": "IT",
        "source": "ANSA"
    },
    {
        "title": "Istat, meno import energia, sale saldo commerciale extra Ue",
        "date_raw": "Fri, 22 Dec 2023 11:38:41 +0100",
        "date": "2023-12-22",
        "url": "https://www.ansa.it/sito/notizie/economia/economia_rss.xml",
        "news_url": "https://www.ansa.it/sito/notizie/economia/2023/12/22/istat-meno-import-energia-sale-saldo-commerciale-extra-ue_77681810-092d-4e73-b58b-2ecb07086683.html",
        "subtitle": "A novembre a 6,2 miliardi. Crollano acquisti da Russia -91%",
        "content": "\n                                                \n            Il forte ribasso dell'import di\nenergia (-38%) dai paesi extra Ue, a novembre, riduce il deficit\nenergetico dell'Italia a 5,18 miliardi contro gli 8,7 di un anno\nfa e migliora il saldo commerciale complessivo. E' quanto si\nlegge nei dati Istat secondo cui il saldo commerciale con i\npaesi extra Ue27 è positivo e pari a +6.224 milioni (+1.841\nmilioni a novembre 2022). L'avanzo nell'interscambio di prodotti\nnon energetici aumenta da 10.555 milioni di novembre 2022 a\n11.410 milioni di novembre 2023. Gli acquisti dalla Russia\nregistrano la flessione tendenziale più ampia (-91,8%). \n                                    \n                                       \n\t\t\t\t          \n                                \n\nRiproduzione riservata © Copyright ANSA\n\n\n\n",
        "ranked": 19,
        "placed": "Economy",
        "epoch": 1703262625.2427957,
        "language": "IT",
        "source": "ANSA"
    },
    {
        "title": "Pirelli, nuova linea di credito da 500 milioni dalle banche",
        "date_raw": "Fri, 22 Dec 2023 11:39:16 +0100",
        "date": "2023-12-22",
        "url": "https://www.ansa.it/sito/notizie/economia/economia_rss.xml",
        "news_url": "https://www.ansa.it/sito/notizie/economia/2023/12/22/pirelli-nuova-linea-di-credito-da-500-milioni-dalle-banche_89c72041-3309-49db-9ec0-9a73e9a7cece.html",
        "subtitle": "Parametrata ai target di decarbonizzazione del nuovo piano",
        "content": "\n                                                \n            Pirelli ha sottoscritto un accordo\ncon un pool di banche internazionali per una linea di credito\ncommitted di tipo revolving per un ammontare di 500 milioni di\neuro con scadenza a 4 anni, nel dicembre 2027. La nuova linea,\nrealizzata nell'ambito della consueta attività di gestione e\nottimizzazione della struttura finanziaria, consentirà di\nrafforzare il margine di liquidità che, a fine settembre, già\ngarantiva le coperture delle scadenze sul debito fino alla fine\ndel 2025.\n                                    \n                                       \n\t\t\t\t    Nell'ambito dell'accordo con le banche il gruppo di\npneumatici potrà parametrare la nuova linea di credito ai nuovi\nScience based target - in linea con il proprio commitment al Net\nzero - che la società definirà nell'ambito del nuovo piano\nindustriale dopo aver raggiunto con due anni di anticipo gli\nobiettivi di decarbonizzazione inizialmente previsti per il\n2025. \n                                    \n                                       \n\t\t\t\t          \n                                \n\nRiproduzione riservata © Copyright ANSA\n\n\n\n",
        "ranked": 18,
        "placed": "Economy",
        "epoch": 1703262625.251433,
        "language": "IT",
        "source": "ANSA"
    },
    {
        "title": "Nel golfo di Aden traffico navi container crollato dell'82%",
        "date_raw": "Fri, 22 Dec 2023 12:58:55 +0100",
        "date": "2023-12-22",
        "url": "https://www.ansa.it/sito/notizie/economia/economia_rss.xml",
        "news_url": "https://www.ansa.it/sito/notizie/economia/2023/12/22/nel-golfo-di-aden-traffico-navi-container-crollato-dell82_e843e135-8e0a-4071-b3e1-7bef3153b64c.html",
        "subtitle": "Analisi Clarkson, ribasso anche per petroliere",
        "content": "\n                                                \n            Il traffico delle navi portacontainer\nnel golfo di Adem, la porta di accesso al mar Rosso e al Canale\ndi Suez dove si sono verificati gli attacchi dei ribelli dello\nYemen, è crollato dell'82% negli ultimi quattro giorni con oltre\n100 imbarcazioni che hanno preso la via del Capo di Buona\nSperanza. Il calcolo arriva dalla società di ricerca Clarkson\ncitata da Bloomberg, secondo cui in ribasso sono anche i\npassaggi di petroliere e altre navi. Le grandi compagnie di\nshipping che hanno annuncito la sospensione della rotta del Mare\nRosso o hanno preso comunque una decisione in tal senso,\nattendono ora l'arrivo della flotta militare guidata dagli Stati\nUniti per rendere sicuro il transito.\n                                    \n                                       \n\t\t\t\t   La rotta attorno all'Africa comporta un allungamento dei\ntempi e del costo dei viaggi oltre a problemi di\napprovvigionamento, per ora limitati ad alcune realtà\nimprenditoriali. Per transitare attraverso il Mar Rosso i costi\ndelle polizze assicurative hanno subito un forte rialzo. \n                                    \n                                       \n\t\t\t\t          \n                                \n\nRiproduzione riservata © Copyright ANSA\n\n\n\n",
        "ranked": 16,
        "placed": "Economy",
        "epoch": 1703262625.27177,
        "language": "IT",
        "source": "ANSA"
    },
    {
        "title": "Borsa: Milano piatta con l'Europa, attesa l'inflazione Usa",
        "date_raw": "Fri, 22 Dec 2023 13:31:20 +0100",
        "date": "2023-12-22",
        "url": "https://www.ansa.it/sito/notizie/economia/economia_rss.xml",
        "news_url": "https://www.ansa.it/sito/notizie/economia/2023/12/22/borsa-milano-piatta-con-leuropa-attesa-linflazione-usa_91877fae-0523-48c9-832d-d8afc9c0fb5a.html",
        "subtitle": "Brilla Diasorin, scende Amplifon",
        "content": "\n                                                \n            Piazza Affari è piatta (+0,05%) al\npari delle altre Borse europee che continuano a oscillare\nintorno alla parità in attesa del Pce core, l'indicatore\nsull'indicatore sull'inflazione più guardato dalla Fed, che\npotrebbe spingere la banca guidata da Jerome Powell a tagliare i\ntassi a partire da marzo prossimo.\n                                    \n                                       \n\t\t\t\tIn questa prospettiva, mentre l'azionariato è al palo con\nFrancoforte -0,06%, Parigi invariata e Londra +0,07%, dopo il\ndato sul Pil nel Regno Unito che rafforza il rischio che il\npaese vada in recessione, sui mercati valutari il dollaro è in\ndiscesa dell'1% sull'euro così come sulle altre monete.\n                                    \n                                       \n\t\t\t\tIn  leggero calo poi i rendimenti dei titoli di Stato: lo spread\nBtp Bund è a 159,8 col rendimento del bond italiano al 3,56%.\n                                    \n                                       \n\t\t\t\tA Milano sul podio si è portata Diasorin (+1,62%), davanti a Eni\n(+0,53%) all'indomani della vendita del 9% di Plenitude e grazie\nal greggio in rialzo. Salgono poi Generali (+0,5%) e Mediobanca\n(+0,4%), annulla i guadagni iniziali Tim (+0,03%). Fuori dal\npaniere principale viene promosso il polo delle macchine da\ncaffè De' Longhi (+2%). Le peggiori sono invece Amplifon\n(-1,23%), Moncler (-0,64%) e Stm (-0,51%). \n                                    \n                                       \n\t\t\t\t          \n                                \n\nRiproduzione riservata © Copyright ANSA\n\n\n\n",
        "ranked": 14,
        "placed": "Economy",
        "epoch": 1703262625.2815864,
        "language": "IT",
        "source": "ANSA"
    },
    {
        "title": "Via libera del Senato alla manovra, passa alla Camera",
        "date_raw": "Fri, 22 Dec 2023 13:14:54 +0100",
        "date": "2023-12-22",
        "url": "https://www.ansa.it/sito/notizie/economia/economia_rss.xml",
        "news_url": "https://www.ansa.it/sito/notizie/economia/2023/12/22/via-libera-del-senato-alla-manovra-passa-alla-camera_76809349-5360-43ad-9db0-03d23e2c1eef.html",
        "subtitle": "I sì sono stati 109, 72 i contrari, 2 gli astenuti",
        "content": "\n                                                \n            Via libera dell'Aula del Senato alla\nmanovra. La legge di bilancio è stata approvata con 109 sì, 72\nno e 2 astenuti.\n                                    \n                                       \n\t\t\t\tIl provvedimento ora passa all'esame della Camera e il via\nlibera finale del Parlamento è previsto - in base agli accordi\nintercorsi tra i gruppi - senza fiducia nella giornata del 29\ndicembre. \n                                    \n                                       \n\t\t\t\t          \n                                \n\nRiproduzione riservata © Copyright ANSA\n\n\n\n",
        "ranked": 15,
        "placed": "Economy",
        "epoch": 1703262625.2904453,
        "language": "IT",
        "source": "ANSA"
    },
    {
        "title": "Manovra, ok del Senato alla fiducia con 112 sì",
        "date_raw": "Fri, 22 Dec 2023 12:34:03 +0100",
        "date": "2023-12-22",
        "url": "https://www.ansa.it/sito/notizie/economia/economia_rss.xml",
        "news_url": "https://www.ansa.it/sito/notizie/economia/2023/12/22/manovra-ok-del-senato-alla-fiducia-con-112-si_09013eaf-3701-45d8-a6d4-16b5da7e6975.html",
        "subtitle": "76 voti contrari e 3 astenuti",
        "content": "\n                                                \n            Via libera del Senato alla fiducia\nsul maxiemendamento sulla manovra con 112 voti favorevoli, 76 no\ne 3 astenuti. L'assemblea ora passerà all'esame della Nota di\nvariazioni di bilancio e al voto finale del provvedimento, che\npoi sarà all'esame della Camera per l'ok definitivo. \n                                    \n                                       \n\t\t\t\t          \n                                \n\nRiproduzione riservata © Copyright ANSA\n\n\n\n",
        "ranked": 17,
        "placed": "Economy",
        "epoch": 1703262625.302891,
        "language": "IT",
        "source": "ANSA"
    },
    {
        "title": "Giorgetti: 'Era mio interesse approvare il Mes ma non c'era aria'",
        "date_raw": "Fri, 22 Dec 2023 16:53:01 +0100",
        "date": "2023-12-22",
        "url": "https://www.ansa.it/sito/notizie/economia/economia_rss.xml",
        "news_url": "https://www.ansa.it/sito/notizie/economia/2023/12/22/giorgetti-sul-mes-nessuno-strappo-ue-non-ha-sempre-ragione_94b8ff2a-f997-48ea-a0b7-d699aafd3aba.html",
        "subtitle": "Dimissioni? 'Consigli opposizioni sempre utili, ma decido io'",
        "content": "\"Sul Mes che ci fossero problemi era noto a tutti. Abbiamo fatto un passo in avanti sul Patto di Stabilità, ma le sfide in Europa sono ben altre. Non è che l'Europa ha sempre ragione\". Così il ministro dell'Economia Giancarlo Giorgetti ha risposto ai giornalisti a margine dell'Aula del Senato. Ai cronisti che gli chiedevano se sul Mes ci fosse stato uno strappo con l'Europa, ha risposto di \"no\". \"Tutto si può migliorare, anche il Mes - ha aggiunto Giorgetti -. Questi trattati sono stati fatti in certi periodi storici, probabilmente anche la storia chiede altri tipi di risposte. Anche il Patto di stabilità, perché si è cambiato? Perché quando fu fatto col vecchio Patto c'era una situazione totalmente diversa e oggi ci sono altri tipi di necessità\". \"Anche per le ambizioni che ha l'Europa\", ha aggiunto. \"Il ministro dell'economia e delle finanze aveva interesse che il Mes fosse approvato per motivazioni di tipo economico e finanziario ma per come si è sviluppato il dibattito negli ultimi giorni, giurì d'onore e cose di questo tipo, mi è sembrato evidente che non c'era aria per l'approvazione. Per motivazioni anche non solo economiche\", ha detto il ministro dell'Economia. A chi gli chiedeva della richiesta delle opposizioni di dimettersi, ha risposto: \"I consigli dell'opposizioni sono sempre utili però permettetemi che poi decido io\". \"Tutto si può migliorare, anche il Mes\".ha spiegato il ministro, intercettato in Senato a margine dell'ok dell'Aula alla manovra, a chi gli chiedeva se il Mes si possa modificare o si possa riaprire la partita. \"Questi trattati sono stati fatti in certi periodi storici, probabilmente anche la storia chiede altri tipi di risposte. Anche il Patto di stabilità, perché si è cambiato? Perché quando fu fatto col vecchio Patto c'era una situazione totalmente diversa e oggi ci sono altri tipi di necessità\". \"Anche per le ambizioni che ha l'Europa\", ha aggiunto.   \"Sul Superbonus, non è che noi viviamo su Marte, ma abbiamo anche i numeri, stiamo aspettando le ultime proiezioni per quanto riguarda il costo\", ha detto il ministro dell'Economia Giorgetti a chi gli chiedeva della proposta di una Sal straordinaria sull'agevolazione. \"Abbiamo un problema di tenuta dei conti pubblici da cui poi facciamo dipendere le decisioni\", ha aggiunto.  \"Ogni mese di Superbonus ci costa 4,5 miliardi che è quello che abbiamo stanziato in aumento per la Sanità per il 2024. Ogni mese di proroga del Superbonus si mangia esattamente lo stanziamento della sanità, se non si capisce questo non si fa un ragionamento onesto sul Superbonus\".Lo ha detto il ministro dell'Economia Giancarlo Giorgetti interpellato sulla possibile proroga della concessione a margine del voto del Senato sulla manovra. \n\nRiproduzione riservata © Copyright ANSA\n\n\n\n",
        "ranked": 12,
        "placed": "Economy",
        "epoch": 1703262625.3142176,
        "language": "IT",
        "source": "ANSA"
    },
    {
        "title": "Ex Ilva: nuovo cda Acciaierie il 28 per delibera su capitale",
        "date_raw": "Fri, 22 Dec 2023 14:19:46 +0100",
        "date": "2023-12-22",
        "url": "https://www.ansa.it/sito/notizie/economia/economia_rss.xml",
        "news_url": "https://www.ansa.it/sito/notizie/economia/2023/12/22/ex-ilva-nuovo-cda-acciaierie-il-28-per-delibera-su-capitale_8e15783f-50cb-4e3b-b6aa-3ef436da9fac.html",
        "subtitle": "Da proporre all'assemblea per il fabbisogno finanziario",
        "content": "\"A seguito dei lavori assembleari della giornata di oggi, Acciaierie d'Italia comunica che è stato convocato un consiglio di amministrazione per il prossimo 28 dicembre, con l'obiettivo di formulare un nuovo testo di delibera da proporre all'assemblea degli Azionisti a sostegno del fabbisogno finanziario della Società\". Lo annuncia Acciaierie in una nota.     \n\nRiproduzione riservata © Copyright ANSA\n\n\n\n",
        "ranked": 11,
        "placed": "Economy",
        "epoch": 1703262625.3294976,
        "language": "IT",
        "source": "ANSA"
    },
    {
        "title": "Via libera del Senato alla manovra, passa alla Camera",
        "date_raw": "Fri, 22 Dec 2023 14:08:14 +0100",
        "date": "2023-12-22",
        "url": "https://www.ansa.it/sito/notizie/economia/economia_rss.xml",
        "news_url": "https://www.ansa.it/sito/notizie/economia/2023/12/22/via-libera-del-senato-alla-manovra-passa-alla-camera_a8e720c5-e236-4d57-9c20-659c8495b022.html",
        "subtitle": "I sì sono stati 109, 72 i contrari, 2 gli astenuti",
        "content": "\n                                                \n            Via libera dell'Aula del Senato\nallamanovra. La legge di bilancio è stata approvata con 109 sì,\n72 no e 2 astenuti. Il provvedimento ora passa all'esame della\nCamera e il via libera finale del Parlamento è previsto - in\nbase agli accordi intercorsi tra i gruppi -  senza fiducia nella\ngiornata del 29 dicembre. \n                                    \n                                       \n\t\t\t\t          \n                                \n\nRiproduzione riservata © Copyright ANSA\n\n\n\n",
        "ranked": 10,
        "placed": "Economy",
        "epoch": 1703262625.343589,
        "language": "IT",
        "source": "ANSA"
    },
    {
        "title": "Superbonus: Giorgetti, decisione dipende da tenuta conti",
        "date_raw": "Fri, 22 Dec 2023 14:08:28 +0100",
        "date": "2023-12-22",
        "url": "https://www.ansa.it/sito/notizie/economia/economia_rss.xml",
        "news_url": "https://www.ansa.it/sito/notizie/economia/2023/12/22/superbonus-giorgetti-decisione-dipende-da-tenuta-conti_398c344c-0115-4c72-9311-b199b223004f.html",
        "subtitle": "'Aspettiamo ultime proiezioni sul costo'",
        "content": "\n                                                \n            \"Sul Superbonus, non è che noi\nviviamo su Marte, ma abbiamo anche i numeri, stiamo aspettando\nle ultime proiezioni per quanto riguarda il costo\". Lo ha detto\nil ministro dell'Economia Giancarlo Giorgetti a chi gli chiedeva\ndella proposta di una Sal straordinaria sull'agevolazione.\n                                    \n                                       \n\t\t\t\t\"Abbiamo un problema di tenuta dei conti pubblici da cui poi\nfacciamo dipendere le decisioni\", ha aggiunto. \n                                    \n                                       \n\t\t\t\t          \n                                \n\nRiproduzione riservata © Copyright ANSA\n\n\n\n",
        "ranked": 9,
        "placed": "Economy",
        "epoch": 1703262625.3538203,
        "language": "IT",
        "source": "ANSA"
    },
    {
        "title": "Manovra: Giorgetti, tempi complicati, aiutiamo famiglie",
        "date_raw": "Fri, 22 Dec 2023 14:08:20 +0100",
        "date": "2023-12-22",
        "url": "https://www.ansa.it/sito/notizie/economia/economia_rss.xml",
        "news_url": "https://www.ansa.it/sito/notizie/economia/2023/12/22/manovra-giorgetti-tempi-complicati-aiutiamo-famiglie_57af1d37-d6fb-4df8-a1bd-d9e149ab29ed.html",
        "subtitle": "'Guerra ha portato inflazione, ignorarlo è ignorare la realtà'",
        "content": "\n                                                \n            \"Abbiamo approvato il bilancio dello\nStato, dove c'è dentro anche quello che abbiamo fatto. Tanti\nl'hanno criticato, siccome viviamo in tempi complicati, speriamo\nnon sempre ci sia una guerra in Europa, abbiamo deciso di\naiutare le famiglie italiane più bisognose proprio nel 2024,\nperché ci siamo resi conto che purtroppo questa guerra ha\nportato anche tanta inflazione nelle case degli italiani.\n                                    \n                                       \n\t\t\t\tIgnorare questo sarebbe ignorare la realtà\". Lo ha detto il\nministro dell'Economia Giancarlo Giorgetti a margine\ndell'approvazione della manovra in Senato. \n                                    \n                                       \n\t\t\t\t          \n                                \n\nRiproduzione riservata © Copyright ANSA\n\n\n\n",
        "ranked": 8,
        "placed": "Economy",
        "epoch": 1703262625.3645737,
        "language": "IT",
        "source": "ANSA"
    },
    {
        "title": "Pichetto firma il decreto sull'Agrivoltaico",
        "date_raw": "Fri, 22 Dec 2023 14:08:33 +0100",
        "date": "2023-12-22",
        "url": "https://www.ansa.it/sito/notizie/economia/economia_rss.xml",
        "news_url": "https://www.ansa.it/sito/notizie/economia/2023/12/22/pichetto-firma-il-decreto-sullagrivoltaico_79f107ac-6cc5-4e33-adc6-74f769953a45.html",
        "subtitle": "Contributi fino al 40% e tariffa incentivante",
        "content": "\n                                                \n            Il Ministro dell'Ambiente e della\nSicurezza Energetica Gilberto Pichetto ha firmato e trasmesso\nalla Corte dei Conti il decreto che incentiva la diffusione\ndell'agrivoltaico innovativo. Con il provvedimento, su cui già\nc'è stato il 'via libera' della Commissione europea, ci si pone\nl'obiettivo di installare almeno 1,04 gigawatt di sistemi\nagrivoltaici avanzati entro il 30 giugno del 2026, attraverso\ndue misure: la concessione, a valere sui fondi PNRR, di un\ncontributo in conto capitale nella misura massima del 40% dei\ncosti ammissibili e una tariffa incentivante sulla produzione di\nenergia elettrica netta immessa in rete.\n                                    \n                                       \n\t\t\t\t   \"La diffusione dell'agrivoltaico - spiega Pichetto - è una\nchiave per la decarbonizzazione in un settore strategico, fatta\nattraverso un uso intelligente e sostenibile del suolo, che\naiuti l'ambiente, la produzione e lo sviluppo delle rinnovabili.\n                                    \n                                       \n\t\t\t\tL'agricoltura italiana, eccellente per la sua qualità\nriconosciuta in tutto il mondo - conclude Pichetto - sarà ancor\npiù protagonista della transizione ambientale ed energetica\".\n                                    \n                                       \n\t\t\t\t   Il contributo in conto capitale è finanziato attraverso\nl'investimento del Pnrr, pari a oltre un miliardo di euro,\nmentre per la tariffa incentivante si stima un importo annuo di\n21 milioni di euro, a valere sugli oneri di sistema.\n                                    \n                                       \n\t\t\t\t   Per garantire il più ampio accesso dell'imprenditoria\nagricola ai benefici promossi, si è stabilito di destinare un\ncontingente di 300 megawatt al solo comparto agricolo per\nimpianti di potenza fino a 1 megawatt, con accesso tramite\nregistri. Un secondo contingente di 740 Mw è invece dedicato sia\nal comparto agricolo che alle associazioni temporanee di\nimprese, che includano almeno un soggetto del comparto agricolo,\ncon accesso tramite la partecipazione a procedure competitive\nper impianti di qualsiasi potenza. Gestore della misura e\ndell'accesso al meccanismo incentivante è il Gse (Gestore\nServizi Energetici). \n                                    \n                                       \n\t\t\t\t          \n                                \n\nRiproduzione riservata © Copyright ANSA\n\n\n\n",
        "ranked": 7,
        "placed": "Economy",
        "epoch": 1703262625.3747518,
        "language": "IT",
        "source": "ANSA"
    },
    {
        "title": "Giorgetti, su Ita-Lufthansa stop Ue, altri approfondimenti",
        "date_raw": "Fri, 22 Dec 2023 13:34:25 +0100",
        "date": "2023-12-22",
        "url": "https://www.ansa.it/sito/notizie/economia/economia_rss.xml",
        "news_url": "https://www.ansa.it/sito/notizie/economia/2023/12/22/giorgetti-su-ita-lufthansa-stop-ue-altri-approfondimenti_aa66900c-5594-494d-a202-6164d4eb1bc7.html",
        "subtitle": "'Ci hanno fatto capire che si va alla fase due'",
        "content": "\n                                                \n            \"Non è che l'Europa ha sempre\nragione. Ad esempio, \"sulla vicenda Ita-Lufthansa ci hanno messo\nun altro stop. Quando hanno torto hanno torto anche loro, non è\nche l'Europa ha sempre ragione e l'Italia ha sempre torto\". Lo\nha detto il ministro dell'Economia Giancarlo Giorgetti\nintercettato in Senato. \"Ci hanno fatto capire che si va alla\ncosiddetta fase due, quindi serviranno altri mesi di\napprofondimenti. Dopo aver fatto esattamente quello che era\nstato prescritto dalla stessa Commissione Ue. Il fatto che\nperdiamo altro tempo non è una cosa positiva\". A chi gli chiede\nse ci siano problemi sulla concorrenza, risponde: \"Secondo\nloro\". \n                                    \n                                       \n\t\t\t\t          \n                                \n\nRiproduzione riservata © Copyright ANSA\n\n\n\n",
        "ranked": 13,
        "placed": "Economy",
        "epoch": 1703262625.384814,
        "language": "IT",
        "source": "ANSA"
    },
    {
        "title": "Fisco: dichiarazioni 2024, pronte le bozze",
        "date_raw": "Fri, 22 Dec 2023 15:35:54 +0100",
        "date": "2023-12-22",
        "url": "https://www.ansa.it/sito/notizie/economia/economia_rss.xml",
        "news_url": "https://www.ansa.it/sito/notizie/economia/2023/12/22/fisco-dichiarazioni-2024-pronte-le-bozze_ed932920-72ae-4c75-81d7-41f655e752c2.html",
        "subtitle": "Novità su Superbonus e la tassazione agevolata per le mance",
        "content": "\n                                                \n            Sul sito dell'Agenzia delle Entrate\nsono state pubblicate le bozze dei modelli 2024, con le relative\nistruzioni, da utilizzare nelle dichiarazioni da presentare il\nprossimo anno.\n                                    \n                                       \n\t\t\t\t   Per i Modelli 730 e Redditi Persone fisiche, le dichiarazioni\nper l'anno d'imposta 2023 presentano diverse novità, tra cui la\ntassazione agevolata delle mance per i lavoratori dipendenti\ndelle strutture ricettive del settore privato, la ridefinizione\ndell'ambito fiscale del lavoro sportivo, la rideterminazione\ndella detrazione spettante al personale del comparto sicurezza e\ndifesa, la modifica del limite di spesa massimo su cui calcolare\nla detrazione per l'acquisto di mobili e di grandi\nelettrodomestici.\n                                    \n                                       \n\t\t\t\t    I modelli recepiscono inoltre le novità relativi agli\naggiornamenti previsti dalla disciplina del Superbonus, alla\ndisciplina di tassazione delle \"cripto-attività\", quelle\nriguardanti il regime forfetario, la disciplina del concordato\npreventivo biennale e il nuovo regime della tassa piatta\nincrementale (cd. flat tax incrementale). \n                                    \n                                       \n\t\t\t\t          \n                                \n\nRiproduzione riservata © Copyright ANSA\n\n\n\n",
        "ranked": 5,
        "placed": "Economy",
        "epoch": 1703262625.4040248,
        "language": "IT",
        "source": "ANSA"
    }
]
